cmp_utilities/__init__.py
cmp_utilities/bigquery.py
cmp_utilities/credential.py
cmp_utilities/datetime_utils.py
cmp_utilities/logging.py
cmp_utilities/monitoring.py
cmp_utilities/secret_manager.py
cmp_utilities-0.0.10.dist-info/LICENSE
cmp_utilities-0.0.10.dist-info/METADATA
cmp_utilities-0.0.10.dist-info/WHEEL
cmp_utilities-0.0.10.dist-info/top_level.txt
cmp_utilities-0.0.10.dist-info/RECORD
