Metadata-Version: 2.1
Name: cmp-utilities
Version: 0.0.10
Summary: Utility modules for Cloud Management Platform
Author-email: Jheel Patel <jheelpatelscientist@gmail.com>
Project-URL: Homepage, https://github.com/extremize/CloudManagementPlatformPublic
Project-URL: Bug Tracker, https://github.com/extremize/CloudManagementPlatformPublic
Classifier: Programming Language :: Python :: 3
Classifier: License :: OSI Approved :: Apache Software License
Classifier: Operating System :: OS Independent
Requires-Python: >=3.7
License-File: LICENSE
Requires-Dist: google-auth (==2.16.0)
Requires-Dist: google-cloud-logging (==3.4.0)
Requires-Dist: google-cloud-secret-manager (==2.16.1)
Requires-Dist: bigquery-schema-generator (==1.5.1)
Requires-Dist: google-cloud-bigquery (==3.4.2)
Requires-Dist: python-dotenv (==0.21.1)
Requires-Dist: pytz (==2023.3)
